<?xml version="1.0" encoding="utf-8"?>
<ArrayOfVolunteer xmlns:xsi="http://www.w3.org/2001/XMLSchema-instance" xmlns:xsd="http://www.w3.org/2001/XMLSchema">
  <Volunteer>
    <Id>258736403</Id>
    <Name>David Cohen</Name>
    <Phone>050-7179112</Phone>
    <Email>davidcohen@gmail.com</Email>
    <Password>Dav112</Password>
    <Address>123 Main St, Cityville</Address>
    <Latitude>29.5575</Latitude>
    <Longitude>34.9522</Longitude>
    <Jobs>Administrator</Jobs>
    <active>false</active>
    <MaxDistance>45</MaxDistance>
    <DistanceType>AirDistance</DistanceType>
  </Volunteer>
  <Volunteer>
    <Id>298533968</Id>
    <Name>Sarah Levi</Name>
    <Phone>050-6573500</Phone>
    <Email>sarahlevi@gmail.com</Email>
    <Password>Sar500</Password>
    <Address>789 Oak St, Villagetown</Address>
    <Latitude>32.0853</Latitude>
    <Longitude>34.9522</Longitude>
    <Jobs>Worker</Jobs>
    <active>true</active>
    <MaxDistance>17</MaxDistance>
    <DistanceType>AirDistance</DistanceType>
  </Volunteer>
  <Volunteer>
    <Id>352567757</Id>
    <Name>Michael Ben-David</Name>
    <Phone>050-2354366</Phone>
    <Email>michaelben-david@gmail.com</Email>
    <Password>Mic366</Password>
    <Address>123 Main St, Cityville</Address>
    <Latitude>31.7683</Latitude>
    <Longitude>35.2137</Longitude>
    <Jobs>Worker</Jobs>
    <active>true</active>
    <MaxDistance>35</MaxDistance>
    <DistanceType>AirDistance</DistanceType>
  </Volunteer>
  <Volunteer>
    <Id>384979152</Id>
    <Name>Rachel Gold</Name>
    <Phone>050-8048772</Phone>
    <Email>rachelgold@gmail.com</Email>
    <Password>Rac772</Password>
    <Address>123 Main St, Cityville</Address>
    <Latitude>32.0853</Latitude>
    <Longitude>35.2137</Longitude>
    <Jobs>Worker</Jobs>
    <active>true</active>
    <MaxDistance>19</MaxDistance>
    <DistanceType>AirDistance</DistanceType>
  </Volunteer>
  <Volunteer>
    <Id>260646817</Id>
    <Name>Daniel Green</Name>
    <Phone>050-8793367</Phone>
    <Email>danielgreen@gmail.com</Email>
    <Password>Dan367</Password>
    <Address>789 Oak St, Villagetown</Address>
    <Latitude>29.5575</Latitude>
    <Longitude>34.9522</Longitude>
    <Jobs>Worker</Jobs>
    <active>false</active>
    <MaxDistance>46</MaxDistance>
    <DistanceType>AirDistance</DistanceType>
  </Volunteer>
  <Volunteer>
    <Id>259265635</Id>
    <Name>Emma Brown</Name>
    <Phone>050-7181813</Phone>
    <Email>emmabrown@gmail.com</Email>
    <Password>Emm813</Password>
    <Address>456 Elm St, Townburg</Address>
    <Latitude>29.5575</Latitude>
    <Longitude>34.7818</Longitude>
    <Jobs>Worker</Jobs>
    <active>true</active>
    <MaxDistance>15</MaxDistance>
    <DistanceType>AirDistance</DistanceType>
  </Volunteer>
  <Volunteer>
    <Id>338386147</Id>
    <Name>James White</Name>
    <Phone>050-2345140</Phone>
    <Email>jameswhite@gmail.com</Email>
    <Password>Jam140</Password>
    <Address>123 Main St, Cityville</Address>
    <Latitude>31.7683</Latitude>
    <Longitude>34.7818</Longitude>
    <Jobs>Worker</Jobs>
    <active>true</active>
    <MaxDistance>26</MaxDistance>
    <DistanceType>AirDistance</DistanceType>
  </Volunteer>
  <Volunteer>
    <Id>358876845</Id>
    <Name>Sophia Black</Name>
    <Phone>050-3205246</Phone>
    <Email>sophiablack@gmail.com</Email>
    <Password>Sop246</Password>
    <Address>456 Elm St, Townburg</Address>
    <Latitude>29.5575</Latitude>
    <Longitude>34.7818</Longitude>
    <Jobs>Worker</Jobs>
    <active>true</active>
    <MaxDistance>30</MaxDistance>
    <DistanceType>AirDistance</DistanceType>
  </Volunteer>
  <Volunteer>
    <Id>377903349</Id>
    <Name>Benjamin Blue</Name>
    <Phone>050-6211777</Phone>
    <Email>benjaminblue@gmail.com</Email>
    <Password>Ben777</Password>
    <Address>789 Oak St, Villagetown</Address>
    <Latitude>32.0853</Latitude>
    <Longitude>35.2137</Longitude>
    <Jobs>Worker</Jobs>
    <active>true</active>
    <MaxDistance>38</MaxDistance>
    <DistanceType>AirDistance</DistanceType>
  </Volunteer>
  <Volunteer>
    <Id>300804979</Id>
    <Name>Olivia Silver</Name>
    <Phone>050-7665564</Phone>
    <Email>oliviasilver@gmail.com</Email>
    <Password>Oli564</Password>
    <Address>789 Oak St, Villagetown</Address>
    <Latitude>32.0853</Latitude>
    <Longitude>34.9522</Longitude>
    <Jobs>Worker</Jobs>
    <active>true</active>
    <MaxDistance>48</MaxDistance>
    <DistanceType>AirDistance</DistanceType>
  </Volunteer>
  <Volunteer>
    <Id>259671046</Id>
    <Name>Noah Gray</Name>
    <Phone>050-4240028</Phone>
    <Email>noahgray@gmail.com</Email>
    <Password>Noa028</Password>
    <Address>789 Oak St, Villagetown</Address>
    <Latitude>31.7683</Latitude>
    <Longitude>35.2137</Longitude>
    <Jobs>Worker</Jobs>
    <active>false</active>
    <MaxDistance>35</MaxDistance>
    <DistanceType>AirDistance</DistanceType>
  </Volunteer>
  <Volunteer>
    <Id>342091575</Id>
    <Name>Emily Rose</Name>
    <Phone>050-8266236</Phone>
    <Email>emilyrose@gmail.com</Email>
    <Password>Emi236</Password>
    <Address>123 Main St, Cityville</Address>
    <Latitude>32.0853</Latitude>
    <Longitude>34.7818</Longitude>
    <Jobs>Worker</Jobs>
    <active>true</active>
    <MaxDistance>31</MaxDistance>
    <DistanceType>AirDistance</DistanceType>
  </Volunteer>
  <Volunteer>
    <Id>273336089</Id>
    <Name>Ethan Adler</Name>
    <Phone>050-4681143</Phone>
    <Email>ethanadler@gmail.com</Email>
    <Password>Eth143</Password>
    <Address>789 Oak St, Villagetown</Address>
    <Latitude>29.5575</Latitude>
    <Longitude>34.9522</Longitude>
    <Jobs>Worker</Jobs>
    <active>true</active>
    <MaxDistance>42</MaxDistance>
    <DistanceType>AirDistance</DistanceType>
  </Volunteer>
  <Volunteer>
    <Id>260703993</Id>
    <Name>Mia Kaplan</Name>
    <Phone>050-5966267</Phone>
    <Email>miakaplan@gmail.com</Email>
    <Password>Mia267</Password>
    <Address>789 Oak St, Villagetown</Address>
    <Latitude>32.0853</Latitude>
    <Longitude>34.9522</Longitude>
    <Jobs>Worker</Jobs>
    <active>false</active>
    <MaxDistance>40</MaxDistance>
    <DistanceType>AirDistance</DistanceType>
  </Volunteer>
  <Volunteer>
    <Id>301992334</Id>
    <Name>Jacob Fisher</Name>
    <Phone>050-4492061</Phone>
    <Email>jacobfisher@gmail.com</Email>
    <Password>Jac061</Password>
    <Address>789 Oak St, Villagetown</Address>
    <Latitude>29.5575</Latitude>
    <Longitude>35.2137</Longitude>
    <Jobs>Worker</Jobs>
    <active>true</active>
    <MaxDistance>46</MaxDistance>
    <DistanceType>AirDistance</DistanceType>
  </Volunteer>
</ArrayOfVolunteer>